wavetest/vsrc/top.v
// Generated by CIRCT firtool-1.62.0
/* verilator lint_off DECLFILENAME */


module top(	// src/main/scala/test2.scala:4:7
  // input        clock,	// src/main/scala/test2.scala:4:7
  //              reset,	// src/main/scala/test2.scala:4:7
  input  [7:0] io_in,	// src/main/scala/test2.scala:5:17
  output [2:0] io_out	// src/main/scala/test2.scala:5:17
);

  assign io_out =
    io_in == 8'h0
      ? 3'h0
      : io_in == 8'h1
          ? 3'h1
          : io_in == 8'h2
              ? 3'h2
              : io_in == 8'h4
                  ? 3'h3
                  : io_in == 8'h8
                      ? 3'h4
                      : io_in == 8'h10
                          ? 3'h5
                          : io_in == 8'h20 ? 3'h6 : {3{io_in == 8'h40}};	// src/main/scala/test2.scala:4:7, :10:12, :12:18, :13:25, :14:25, :15:25, :16:25, :17:25, :18:26, :19:26, :20:26
endmodule

wavetest/wave.vcd
$version Generated by VerilatedVcd $end
$timescale 1ps $end

 $scope module TOP $end
  $var wire  8 # io_in [7:0] $end
  $var wire  3 $ io_out [2:0] $end
  $scope module top $end
   $var wire  8 # io_in [7:0] $end
   $var wire  3 $ io_out [2:0] $end
  $upscope $end
 $upscope $end
$enddefinitions $end


#0
b01000000 #
b111 $
#1
b00100000 #
b110 $
#2
b01000000 #
b111 $
#3
b00100000 #
b110 $
#4
b01000000 #
b111 $
#5
b00100000 #
b110 $
#6
b01000000 #
b111 $
#7
b00100000 #
b110 $
#8
b01000000 #
b111 $
#9
b00100000 #
b110 $
